MANIFEST.in
README.txt
setup.py
Wave.egg-info/PKG-INFO
Wave.egg-info/SOURCES.txt
Wave.egg-info/dependency_links.txt
Wave.egg-info/top_level.txt
doc/_build/html/genindex.html
doc/_build/html/index.html
doc/_build/html/intro.html
doc/_build/html/modules.html
doc/_build/html/py-modindex.html
doc/_build/html/search.html
doc/_build/html/tutorial.html
doc/_build/html/_static/alert_info_32.png
doc/_build/html/_static/alert_warning_32.png
doc/_build/html/_static/basic.css
doc/_build/html/_static/bg-page.png
doc/_build/html/_static/bullet_orange.png
doc/_build/html/_static/default.css
doc/_build/html/_static/file.png
doc/_build/html/_static/haiku.css
doc/_build/html/_static/minus.png
doc/_build/html/_static/plus.png
doc/_build/html/_static/pygments.css
wave/demos/MM2.py
wave/demos/__init__.py
wave/demos/operations.py
wave/tests/MISEtest.py
wave/tests/__init__.py
wave/tests/wavelib/__init__.py
wave/tests/wavelib/operations_tests.py
wave/wavegui/__init__.py
wave/wavegui/exceptions.py
wave/wavegui/grid.py
wave/wavegui/images.py
wave/wavegui/wavegui.py
wave/wavelib/__init__.py
wave/wavelib/dbif.py
wave/wavelib/metamodel.py
wave/wavelib/operations.py