Metadata-Version: 1.0
Name: Wave
Version: 0.0.2
Summary: Whole Architecture Verification
Home-page: http://packages.python.org/Wave/
Author: P Henderson and M J Henderson
Author-email: matthew.james.henderson@gmail.com
License: UNKNOWN
Download-URL: http://pypi.python.org/pypi/Wave/
Keywords: wave verification
Platform: UNKNOWN
Classifier: Programming Language :: Python
Classifier: Environment :: Other Environment
Classifier: Intended Audience :: Developers
Classifier: License :: OSI Approved :: GNU Library or Lesser General Public License (LGPL)
Classifier: Operating System :: OS Independent
Classifier: Topic :: Software Development :: Libraries :: Python Modules
